json_protobuf/__init__.py
json_protobuf/__main__.py
json_protobuf/generator.py
json_protobuf-2.0.1.dist-info/entry_points.txt
json_protobuf-2.0.1.dist-info/LICENSE
json_protobuf-2.0.1.dist-info/METADATA
json_protobuf-2.0.1.dist-info/WHEEL
json_protobuf-2.0.1.dist-info/RECORD
